{"cameraMode":{"drawMode":0,"name":"Shaded","section":"Shading Mode"},"sceneLighting":true,"audioPlay":false,"sceneViewState":{"m_AlwaysRefresh":false,"showFog":true,"showSkybox":true,"showFlares":true,"showImageEffects":true,"showParticleSystems":true,"showVisualEffectGraphs":true,"m_FxEnabled":true},"in2DMode":false,"pivot":{"x":6.349882125854492,"y":1.2081584930419922,"z":-54.560142517089847},"rotation":{"x":-0.2529420256614685,"y":-0.16922487318515778,"z":0.04505405202507973,"w":-0.951615035533905},"size":34.11703872680664,"orthographic":false}